limitedinteraction/VERSION
limitedinteraction/__init__.py
limitedinteraction/__main__.py
limitedinteraction/cmd.py
limitedinteraction/images/alert_large.png
limitedinteraction/images/alert_small.png
limitedinteraction/images/clock_large.png
limitedinteraction/images/clock_small.png
limitedinteraction/images/cloud_large.png
limitedinteraction/images/cloud_small.png
limitedinteraction/images/error_large.png
limitedinteraction/images/error_small.png
limitedinteraction/images/find_large.png
limitedinteraction/images/find_small.png
limitedinteraction/images/gear_large.png
limitedinteraction/images/gear_small.png
limitedinteraction/images/info_large.png
limitedinteraction/images/info_small.png
limitedinteraction/images/light_large.png
limitedinteraction/images/light_small.png
limitedinteraction/images/lock_large.png
limitedinteraction/images/lock_small.png
limitedinteraction/images/question_large.png
limitedinteraction/images/question_small.png
limitedinteraction/images/warning_large.png
limitedinteraction/images/warning_small.png
limitedinteraction-1.0.dist-info/LICENSE.txt
limitedinteraction-1.0.dist-info/METADATA
limitedinteraction-1.0.dist-info/WHEEL
limitedinteraction-1.0.dist-info/top_level.txt
limitedinteraction-1.0.dist-info/RECORD
