Metadata-Version: 2.1
Name: limitedinteraction
Version: 1.0
Summary: Simple dialog windows for scripters and scientists.
Home-page: https://felixchenier.uqam.ca/limitedinteraction/
Author: Félix Chénier
Author-email: chenier.felix@uqam.ca
License: Apache
Project-URL: Documentation, https://felixchenier.uqam.ca/limitedinteraction/api.html
Project-URL: Source, https://github.com/felixchenier/limitedinteraction/
Project-URL: Tracker, https://github.com/felixchenier/limitedinteraction/issues
Classifier: Development Status :: 3 - Alpha
Classifier: Intended Audience :: Developers
Classifier: Intended Audience :: Science/Research
Classifier: License :: OSI Approved :: Apache Software License
Classifier: Natural Language :: English
Classifier: Operating System :: MacOS
Classifier: Operating System :: Microsoft :: Windows
Classifier: Operating System :: POSIX
Classifier: Programming Language :: Python :: 3
Classifier: Topic :: Software Development :: User Interfaces
Requires-Python: >=3.7
License-File: LICENSE.txt
